cutthelog.py
cutthelog-0.9.2.dist-info/LICENSE
cutthelog-0.9.2.dist-info/METADATA
cutthelog-0.9.2.dist-info/WHEEL
cutthelog-0.9.2.dist-info/entry_points.txt
cutthelog-0.9.2.dist-info/top_level.txt
cutthelog-0.9.2.dist-info/RECORD
