Metadata-Version: 2.1
Name: cutthelog
Version: 0.9.2
Summary: Print an unseen tailing part of a log file
Home-page: https://github.com/yaznahar/cutthelog
Author: Alexander Larin
Author-email: yaznahar@yandex.ru
License: MIT license
Classifier: Development Status :: 4 - Beta
Classifier: Environment :: Console
Classifier: Intended Audience :: Developers
Classifier: Intended Audience :: System Administrators
Classifier: Natural Language :: English
Classifier: License :: OSI Approved :: MIT License
Classifier: Topic :: System :: Systems Administration
Classifier: Topic :: Text Processing :: Filters
Classifier: Topic :: Utilities
Classifier: Operating System :: OS Independent
Classifier: Programming Language :: Python
Classifier: Programming Language :: Python :: 2
Classifier: Programming Language :: Python :: 2.7
Classifier: Programming Language :: Python :: 3
Classifier: Programming Language :: Python :: 3.5
Classifier: Programming Language :: Python :: 3.6
Classifier: Programming Language :: Python :: 3.7
Classifier: Programming Language :: Python :: 3.8
Classifier: Programming Language :: Python :: 3.9
Classifier: Programming Language :: Python :: 3.10
Classifier: Programming Language :: Python :: 3.11
Classifier: Programming Language :: Python :: Implementation :: CPython
License-File: LICENSE
